{
  "bioguide_id": "B001325",
  "name": "Sheri Biggs",
  "party": "R",
  "state": "SC",
  "district": "3",
  "chamber": "house",
  "contacts": {
    "dc_phone": {
      "value": "(202) 225-5301",
      "status": "verified",
      "source": "https://sheribiggs.house.gov/contact",
      "verified_date": "2026-03-27"
    },
    "dc_fax": {
      "value": "",
      "status": "placeholder",
      "source": "",
      "verified_date": ""
    },
    "web_form_url": {
      "value": "https://sheribiggs.house.gov/address_authentication?form=/contact/email-me",
      "status": "verified",
      "source": "https://sheribiggs.house.gov/contact",
      "verified_date": "2026-03-27"
    },
    "twitter": {
      "value": "@RepSheriBiggs",
      "status": "verified",
      "source": "https://ballotpedia.org/Sheri_Biggs",
      "verified_date": "2026-03-27"
    },
    "facebook": {
      "value": "RepSheriBiggs",
      "status": "verified",
      "source": "https://ballotpedia.org/Sheri_Biggs",
      "verified_date": "2026-03-27"
    },
    "instagram": {
      "value": "repsheribiggs",
      "status": "verified",
      "source": "https://ballotpedia.org/Sheri_Biggs",
      "verified_date": "2026-03-27"
    },
    "bluesky": {
      "value": "",
      "status": "placeholder",
      "source": "",
      "verified_date": ""
    },
    "youtube": {
      "value": "@repsheribiggs",
      "status": "verified",
      "source": "https://www.youtube.com/@RepSheriBiggs",
      "verified_date": "2026-03-27"
    },
    "truth_social": {
      "value": "",
      "status": "placeholder",
      "source": "",
      "verified_date": ""
    },
    "campaign_site": {
      "value": "https://www.sheribiggs.com",
      "status": "verified",
      "source": "https://ballotpedia.org/Sheri_Biggs",
      "verified_date": "2026-03-27"
    }
  },
  "state_offices": [
    {
      "city": {
        "value": "Anderson",
        "status": "verified",
        "source": "",
        "verified_date": "2026-03-27"
      },
      "address": {
        "value": "303 West Beltline Blvd, Anderson, SC 29625",
        "status": "verified",
        "source": "",
        "verified_date": "2026-03-27"
      },
      "phone": {
        "value": "(864) 224-7401",
        "status": "verified",
        "source": "",
        "verified_date": "2026-03-27"
      },
      "fax": {
        "value": "",
        "status": "placeholder",
        "source": "",
        "verified_date": "2026-03-27"
      }
    }
  ],
  "metadata": {
    "created": "2026-03-26T21:30:17.312548+00:00",
    "last_updated": "2026-03-27T08:40:38.567327+00:00",
    "verification_notes": ""
  }
}
