{
  "bioguide_id": "G000559",
  "name": "John Garamendi",
  "party": "D",
  "state": "CA",
  "district": "8",
  "chamber": "house",
  "contacts": {
    "dc_phone": {
      "value": "(202) 225-1880",
      "status": "verified",
      "source": "https://www.billtrack50.com/legislatordetail/15984",
      "verified_date": "2026-03-27"
    },
    "dc_fax": {
      "value": "(202) 225-5914",
      "status": "verified",
      "source": "https://www.billtrack50.com/legislatordetail/15984",
      "verified_date": "2026-03-27"
    },
    "web_form_url": {
      "value": "https://garamendi.house.gov/contact",
      "status": "verified",
      "source": "https://garamendi.house.gov/contact",
      "verified_date": "2026-03-27"
    },
    "twitter": {
      "value": "@RepGaramendi",
      "status": "verified",
      "source": "https://x.com/RepGaramendi",
      "verified_date": "2026-03-27"
    },
    "facebook": {
      "value": "https://www.facebook.com/repgaramendi",
      "status": "verified",
      "source": "https://www.facebook.com/repgaramendi/",
      "verified_date": "2026-03-27"
    },
    "instagram": {
      "value": "@repgaramendi",
      "status": "verified",
      "source": "https://www.instagram.com/repgaramendi/",
      "verified_date": "2026-03-27"
    },
    "bluesky": {
      "value": "@repgaramendi.bsky.social",
      "status": "verified",
      "source": "https://bsky.app/profile/repgaramendi.bsky.social",
      "verified_date": "2026-03-27"
    },
    "youtube": {
      "value": "",
      "status": "placeholder",
      "source": "",
      "verified_date": ""
    },
    "truth_social": {
      "value": "",
      "status": "placeholder",
      "source": "",
      "verified_date": ""
    },
    "campaign_site": {
      "value": "https://www.garamendi.org",
      "status": "verified",
      "source": "https://www.garamendi.org/",
      "verified_date": "2026-03-27"
    }
  },
  "state_offices": [
    {
      "city": {
        "value": "Fairfield",
        "status": "verified",
        "source": "",
        "verified_date": "2026-03-27"
      },
      "address": {
        "value": "1261 Travis Boulevard, Suite 100, Fairfield, CA 94533",
        "status": "verified",
        "source": "",
        "verified_date": "2026-03-27"
      },
      "phone": {
        "value": "(707) 438-1822",
        "status": "verified",
        "source": "",
        "verified_date": "2026-03-27"
      },
      "fax": {
        "value": "(707) 438-0523",
        "status": "verified",
        "source": "",
        "verified_date": "2026-03-27"
      }
    },
    {
      "city": {
        "value": "Vallejo",
        "status": "verified",
        "source": "",
        "verified_date": "2026-03-27"
      },
      "address": {
        "value": "420 Virginia Street, Suite 1C, Vallejo, CA 94590",
        "status": "verified",
        "source": "",
        "verified_date": "2026-03-27"
      },
      "phone": {
        "value": "(707) 645-1888",
        "status": "verified",
        "source": "",
        "verified_date": "2026-03-27"
      },
      "fax": {
        "value": "(707) 438-0523",
        "status": "verified",
        "source": "",
        "verified_date": "2026-03-27"
      }
    },
    {
      "city": {
        "value": "Richmond",
        "status": "verified",
        "source": "",
        "verified_date": "2026-03-27"
      },
      "address": {
        "value": "440 Civic Center Plaza, 2nd Floor, Richmond, CA 94804",
        "status": "verified",
        "source": "",
        "verified_date": "2026-03-27"
      },
      "phone": {
        "value": "(510) 620-1001",
        "status": "verified",
        "source": "",
        "verified_date": "2026-03-27"
      },
      "fax": {
        "value": "(707) 438-0523",
        "status": "verified",
        "source": "",
        "verified_date": "2026-03-27"
      }
    }
  ],
  "metadata": {
    "created": "2026-03-26T21:30:13.824815+00:00",
    "last_updated": "2026-03-27T10:10:37.492687+00:00",
    "verification_notes": "house.gov returned 403; verified via BillTrack50, ArtVallejo, web search snippets from house.gov office pages, and social media profile pages"
  }
}
