{
  "bioguide_id": "H001047",
  "name": "James A. Himes",
  "party": "D",
  "state": "CT",
  "district": "4",
  "chamber": "house",
  "contacts": {
    "dc_phone": {
      "value": "(202) 225-5541",
      "status": "verified",
      "source": "https://clerk.house.gov/members/H001047",
      "verified_date": "2026-03-27"
    },
    "dc_fax": {
      "value": "(202) 225-9629",
      "status": "verified",
      "source": "https://www.fairfieldct.org/government/federal_delegation.php",
      "verified_date": "2026-03-27"
    },
    "web_form_url": {
      "value": "https://himes.house.gov/contact-me",
      "status": "verified",
      "source": "https://himes.house.gov/contact-me",
      "verified_date": "2026-03-27"
    },
    "twitter": {
      "value": "",
      "status": "placeholder",
      "source": "",
      "verified_date": ""
    },
    "facebook": {
      "value": "",
      "status": "placeholder",
      "source": "",
      "verified_date": ""
    },
    "instagram": {
      "value": "",
      "status": "placeholder",
      "source": "",
      "verified_date": ""
    },
    "bluesky": {
      "value": "",
      "status": "placeholder",
      "source": "",
      "verified_date": ""
    },
    "youtube": {
      "value": "",
      "status": "placeholder",
      "source": "",
      "verified_date": ""
    },
    "truth_social": {
      "value": "",
      "status": "placeholder",
      "source": "",
      "verified_date": ""
    },
    "campaign_site": {
      "value": "",
      "status": "placeholder",
      "source": "",
      "verified_date": ""
    }
  },
  "state_offices": [
    {
      "city": {
        "value": "Bridgeport",
        "status": "verified",
        "source": "",
        "verified_date": "2026-03-27"
      },
      "address": {
        "value": "350 Fairfield Ave., Suite 603, Bridgeport, CT 06604",
        "status": "verified",
        "source": "",
        "verified_date": "2026-03-27"
      },
      "phone": {
        "value": "(203) 333-6600",
        "status": "verified",
        "source": "",
        "verified_date": "2026-03-27"
      },
      "fax": {
        "value": "(203) 333-6655",
        "status": "verified",
        "source": "",
        "verified_date": "2026-03-27"
      }
    },
    {
      "city": {
        "value": "Stamford",
        "status": "verified",
        "source": "",
        "verified_date": "2026-03-27"
      },
      "address": {
        "value": "888 Washington Blvd., 10th Floor, Stamford, CT 06901",
        "status": "verified",
        "source": "",
        "verified_date": "2026-03-27"
      },
      "phone": {
        "value": "(203) 353-9400",
        "status": "verified",
        "source": "",
        "verified_date": "2026-03-27"
      },
      "fax": {
        "value": "(203) 323-1793",
        "status": "verified",
        "source": "",
        "verified_date": "2026-03-27"
      }
    }
  ],
  "metadata": {
    "created": "2026-03-26T21:30:14.336652+00:00",
    "last_updated": "2026-03-27T10:27:21.871038+00:00",
    "verification_notes": ""
  }
}
